runchecked/__init__.py
runchecked/health_checked_context.py
runchecked-0.1.1.dist-info/LICENSE
runchecked-0.1.1.dist-info/METADATA
runchecked-0.1.1.dist-info/WHEEL
runchecked-0.1.1.dist-info/top_level.txt
runchecked-0.1.1.dist-info/RECORD
