Metadata-Version: 2.1
Name: runchecked
Version: 0.1.1
Summary: Python utility library to run commands in a checked fashion and report the result to Healthchecks.io
Home-page: https://git.hel.freakybytes.net/martin/run-checked
Author: Martin Peters
Author-email: 
License: UNKNOWN
Platform: UNKNOWN
Classifier: Development Status :: 3 - Alpha
Classifier: Programming Language :: Python :: 3
Classifier: Programming Language :: Python :: 3.7
Classifier: Programming Language :: Python :: 3 :: Only
Classifier: Intended Audience :: System Administrators
Classifier: Topic :: Utilities
Classifier: License :: OSI Approved :: MIT License
Requires-Python: >=3.6
